runway/__init__.py
runway/__version__.py
runway/data_types.py
runway/exceptions.py
runway/io.py
runway/model.py
runway/utils.py
runway_python-0.6.1.dist-info/LICENSE
runway_python-0.6.1.dist-info/METADATA
runway_python-0.6.1.dist-info/WHEEL
runway_python-0.6.1.dist-info/top_level.txt
runway_python-0.6.1.dist-info/RECORD
