Metadata-Version: 2.1
Name: runway-python
Version: 0.6.1
Summary: Helper library for creating Runway models
Home-page: https://github.com/runwayml/model-sdk
Author: Runway AI, Inc.
Author-email: support@runwayml.com
License: UNKNOWN
Platform: UNKNOWN
Classifier: License :: OSI Approved :: MIT License
Classifier: Operating System :: OS Independent
Classifier: Development Status :: 4 - Beta
Classifier: Topic :: Software Development :: Libraries :: Python Modules
Classifier: Programming Language :: Python :: 3.6
Classifier: Programming Language :: Python :: 3.7
Requires-Python: >=3.6
Requires-Dist: Flask (>=0.12.2)
Requires-Dist: Flask-Cors (>=3.0.2)
Requires-Dist: Flask-Compress (>=1.3.1)
Requires-Dist: numpy (>=1.15.0)
Requires-Dist: Pillow (>=4.3.0)
Requires-Dist: gevent (>=1.4.0)
Requires-Dist: six (>=1.12.0)
Requires-Dist: colorcet (>=2.0.1)
Requires-Dist: Flask-Sockets (==0.2.1)
Requires-Dist: scipy (>=1.2.1)
Requires-Dist: urllib3[secure] (>=1.25.7)
Requires-Dist: Unidecode (>=1.1.1)
Requires-Dist: flask-compress (>=1.3.1)
Requires-Dist: imageio (>=2.5.0)
